acoustipy/Database.py
acoustipy/Params.py
acoustipy/TMM.py
acoustipy/__init__.py
acoustipy-0.1.0.dist-info/METADATA
acoustipy-0.1.0.dist-info/WHEEL
acoustipy-0.1.0.dist-info/licenses/LICENSE
acoustipy-0.1.0.dist-info/RECORD
