Metadata-Version: 2.1
Name: acoustipy
Version: 0.1.0
Summary: Tools for characterizing the acoustic performance of porous materials.
Author-email: Jacob Peterson <jdpeterman72@gmail.com>
License-File: LICENSE
Classifier: License :: OSI Approved :: MIT License
Classifier: Operating System :: OS Independent
Classifier: Programming Language :: Python :: 3
Requires-Python: >=3.9
Requires-Dist: matplotlib
Requires-Dist: numpy
Requires-Dist: pandas
Requires-Dist: scipy
